Metadata-Version: 2.1
Name: BanglaAI
Version: 0.0.1
Summary: Build Bangla AI powered Bengali Applications
Home-page: https://www.banglaai.org/tools/banglaai
Author: Md Rashad Al Hasan Rony
Author-email: banglaai.org@gmail.com
License: Apache License 2.0
License-File: LICENSE
